FIFO/fifo.v
module fifo#(parameter N = 8 , W = 4)(input clk, reset,read_enable,write_enable,
										input [N-1:0] w_data,
										output [N-1:0]r_data,
										output full_flag , empty_flag,
										output reg valid
										);

reg [N-1 : 0] mem [2**W - 1 : 0];
reg [W-1 : 0 ]r_ptr_reg, w_ptr_reg , r_ptr_next,w_ptr_next,w_ptr_succ,r_ptr_succ;
reg full_reg , empty_reg , full_next , empty_next;


always @ (posedge clk or posedge reset)
begin
if(reset)
begin
	r_ptr_reg <= 0;
	w_ptr_reg <= 0;
	full_reg <= 0;
	empty_reg <=1;
	full_next <= 0;
	empty_next <= 0;
	valid <=0;
end
else begin
	r_ptr_reg <= r_ptr_next;
	w_ptr_reg <= w_ptr_next;
	full_reg <= full_next;
	empty_reg <=empty_next;
end
end

always @ *
begin
		r_ptr_succ = r_ptr_reg + 1;
		w_ptr_succ = w_ptr_reg + 1;
		r_ptr_next = r_ptr_reg;
		w_ptr_next = w_ptr_reg;
		full_next = full_reg;
		empty_next <= empty_reg;

case ({read_enable,write_enable})
0 : 	begin
		end

1 : if(!full_reg) //write
		begin
			w_ptr_next = w_ptr_reg + 1;
			empty_next = 0;
			if(w_ptr_succ == r_ptr_reg)
				full_next = 1;
		end

2 : if(!empty_reg) //read
		begin
			r_ptr_next = r_ptr_reg + 1;
			full_next = 0;
			if(r_ptr_succ == w_ptr_reg)
				empty_next = 1;
		end

3 : begin
		r_ptr_next <= r_ptr_reg + 1;
		w_ptr_next <= w_ptr_reg + 1;
	 end
endcase
end

always @(posedge clk)
	if(write_enable && ~full_reg)
		mem[w_ptr_reg] <= w_data;

assign r_data = mem[r_ptr_reg];
assign full_flag = full_reg;
assign empty_flag = empty_reg;
assign vld = w_ptr_next != r_ptr_next;
endmodule

FIFO/tb.v
`include "fifo.v"

module tb;
reg clk = 0;
reg reset, read_enable , write_enable;
reg [7:0]w_data;
wire [7:0]r_data;
wire full_flag , empty_flag;

fifo inst1 (.clk(clk),.reset(reset),.read_enable(read_enable),.write_enable(write_enable),
			.w_data(w_data),.r_data(r_data),.full_flag(full_flag),.empty_flag(empty_flag));
always
#2 clk = ~clk;

initial
begin
read_enable = 0;
write_enable = 0;
@(negedge clk)
reset = 1;
@(negedge clk)
reset = 0;
@(negedge clk)
write_enable <= 1;w_data <= 8'd10;	
@(negedge clk)
 w_data = 8'd4;
@(negedge clk)
 w_data = 8'd6;
@(negedge clk)
 w_data = 8'd5;
@(negedge clk)
 w_data = 8'd3;
@(negedge clk)
 w_data = 8'd2;
@(negedge clk)
w_data = 8'd1;
@(negedge clk)
 w_data = 8'd9;
@(negedge clk)
read_enable <= 1; 
write_enable <= 0;
@(negedge clk)
read_enable <= 0; 
end

initial
#100 $finish;

initial
begin
$dumpfile("fifo.vcd");
$dumpvars(0,tb);
end

endmodule

FIFO/fifo.vcd
$date
	Wed Aug 12 19:20:04 2020
$end
$version
	Icarus Verilog
$end
$timescale
	1s
$end
$scope module tb $end
$var wire 8 ! r_data [7:0] $end
$var wire 1 " full_flag $end
$var wire 1 # empty_flag $end
$var reg 1 $ clk $end
$var reg 1 % read_enable $end
$var reg 1 & reset $end
$var reg 8 ' w_data [7:0] $end
$var reg 1 ( write_enable $end
$scope module inst1 $end
$var wire 1 $ clk $end
$var wire 1 # empty_flag $end
$var wire 1 " full_flag $end
$var wire 8 ) r_data [7:0] $end
$var wire 1 % read_enable $end
$var wire 1 & reset $end
$var wire 8 * w_data [7:0] $end
$var wire 1 ( write_enable $end
$var wire 1 + vld $end
$var reg 1 , empty_next $end
$var reg 1 - empty_reg $end
$var reg 1 . full_next $end
$var reg 1 / full_reg $end
$var reg 4 0 r_ptr_next [3:0] $end
$var reg 4 1 r_ptr_reg [3:0] $end
$var reg 4 2 r_ptr_succ [3:0] $end
$var reg 1 3 valid $end
$var reg 4 4 w_ptr_next [3:0] $end
$var reg 4 5 w_ptr_reg [3:0] $end
$var reg 4 6 w_ptr_succ [3:0] $end
$upscope $end
$upscope $end
$enddefinitions $end
#0
$dumpvars
bx 6
bx 5
bx 4
x3
bx 2
bx 1
bx 0
x/
x.
x-
x,
x+
bx *
bx )
0(
bx '
x&
0%
0$
x#
x"
bx !
$end
#2
1$
#4
0+
b0 4
b0 0
b1 6
b1 2
03
1,
0.
1#
1-
0"
0/
b0 5
b0 1
1&
0$
#6
0,
1$
#8
0&
0$
#10
0#
0-
1$
#12
1+
b1 4
b1010 '
b1010 *
1(
0$
#14
b10 4
b10 6
b1010 !
b1010 )
b1 5
1$
#16
b100 '
b100 *
0$
#18
b11 4
b11 6
b10 5
1$
#20
b110 '
b110 *
0$
#22
b100 4
b100 6
b11 5
1$
#24
b101 '
b101 *
0$
#26
b101 4
b101 6
b100 5
1$
#28
b11 '
b11 *
0$
#30
b110 4
b110 6
b101 5
1$
#32
b10 '
b10 *
0$
#34
b111 4
b111 6
b110 5
1$
#36
b1 '
b1 *
0$
#38
b1000 4
b1000 6
b111 5
1$
#40
b1001 '
b1001 *
0$
#42
b1001 4
b1001 6
b1000 5
1$
#44
b1 0
b1000 4
0(
1%
0$
#46
b10 0
b10 2
b100 !
b100 )
b1 1
1$
#48
b1 0
0%
0$
