mod-m counter/mod_m.v
module mod_m#(parameter N = 8 , m = 5)(input reset,clk,
										output [N-1 : 0] out,
										output tick);
reg [N-1 : 0] r_reg ; 
wire [N-1 : 0]r_next;

always @(posedge clk or posedge reset)
if(reset)
r_reg <= 0;
else begin
	r_reg <= r_next;
end

assign r_next = (r_reg == m-1) ? 0 : r_reg + 1;
assign tick = (r_reg == m-1)?1:0;
assign out = r_reg;

endmodule

mod-m counter/tb.v
`include "mod_m.v"

module tb;
reg reset, clk=0;
wire [7:0] out;
wire tick;

mod_m inst1 (.reset(reset),.clk(clk),.out(out),.tick(tick));

always 
#1 clk = ~clk;

initial 
begin
#2 reset =1;
#2 reset = 0;
#30 $finish;
end

initial
begin
	$monitor("out = %d , tick = %b",out,tick);
	$dumpfile("lol.vcd");
	$dumpvars(0,tb);
end

endmodule

mod-m counter/lol.vcd
$date
	Thu Aug 13 19:26:38 2020
$end
$version
	Icarus Verilog
$end
$timescale
	1s
$end
$scope module tb $end
$var wire 1 ! tick $end
$var wire 8 " out [7:0] $end
$var reg 1 # clk $end
$var reg 1 $ reset $end
$scope module inst1 $end
$var wire 1 # clk $end
$var wire 8 % out [7:0] $end
$var wire 1 $ reset $end
$var wire 1 ! tick $end
$var wire 8 & r_next [7:0] $end
$var reg 8 ' r_reg [7:0] $end
$upscope $end
$upscope $end
$enddefinitions $end
#0
$dumpvars
bx '
bx &
bx %
x$
0#
bx "
x!
$end
#1
1#
#2
0!
b1 &
b0 "
b0 %
b0 '
0#
1$
#3
1#
#4
0#
0$
#5
b10 &
b1 "
b1 %
b1 '
1#
#6
0#
#7
b11 &
b10 "
b10 %
b10 '
1#
#8
0#
#9
b100 &
b11 "
b11 %
b11 '
1#
#10
0#
#11
1!
b0 &
b100 "
b100 %
b100 '
1#
#12
0#
#13
0!
b1 &
b0 "
b0 %
b0 '
1#
#14
0#
#15
b10 &
b1 "
b1 %
b1 '
1#
#16
0#
#17
b11 &
b10 "
b10 %
b10 '
1#
#18
0#
#19
b100 &
b11 "
b11 %
b11 '
1#
#20
0#
#21
1!
b0 &
b100 "
b100 %
b100 '
1#
#22
0#
#23
0!
b1 &
b0 "
b0 %
b0 '
1#
#24
0#
#25
b10 &
b1 "
b1 %
b1 '
1#
#26
0#
#27
b11 &
b10 "
b10 %
b10 '
1#
#28
0#
#29
b100 &
b11 "
b11 %
b11 '
1#
#30
0#
#31
1!
b0 &
b100 "
b100 %
b100 '
1#
#32
0#
#33
0!
b1 &
b0 "
b0 %
b0 '
1#
